firewheel_repo_windows/__init__.py
firewheel_repo_windows/base_windows_objects/MANIFEST
firewheel_repo_windows/base_windows_objects/README.rst
firewheel_repo_windows/base_windows_objects/create_powershell_wrapper.ps1
firewheel_repo_windows/base_windows_objects/model_component_objects.py
firewheel_repo_windows/base_windows_objects/vm_resources/add_remote_desktop_user.bat
firewheel_repo_windows/base_windows_objects/vm_resources/autologon.ps1
firewheel_repo_windows/base_windows_objects/vm_resources/change_password.ps1
firewheel_repo_windows/base_windows_objects/vm_resources/check_email.ps1
firewheel_repo_windows/base_windows_objects/vm_resources/cleanup.ps1
firewheel_repo_windows/base_windows_objects/vm_resources/configure_ips.ps1
firewheel_repo_windows/base_windows_objects/vm_resources/create_smb_share.ps1
firewheel_repo_windows/base_windows_objects/vm_resources/disable_smbv1.ps1
firewheel_repo_windows/base_windows_objects/vm_resources/enable_file_sharing.ps1
firewheel_repo_windows/base_windows_objects/vm_resources/enable_rdp.ps1
firewheel_repo_windows/base_windows_objects/vm_resources/grant_smb_access.ps1
firewheel_repo_windows/base_windows_objects/vm_resources/manage_network_share.ps1
firewheel_repo_windows/base_windows_objects/vm_resources/rearm_windows.ps1
firewheel_repo_windows/base_windows_objects/vm_resources/remove_autologon.ps1
firewheel_repo_windows/base_windows_objects/vm_resources/run_smb_gen.ps1
firewheel_repo_windows/base_windows_objects/vm_resources/run_task.ps1
firewheel_repo_windows/base_windows_objects/vm_resources/set_hostname.ps1
firewheel_repo_windows/base_windows_objects/vm_resources/smb_traffic_gen.ps1
firewheel_repo_windows/base_windows_objects/vm_resources/wget.ps1
firewheel_repo_windows/configure_domain/MANIFEST
firewheel_repo_windows/configure_domain/README.rst
firewheel_repo_windows/configure_domain/plugin.py
firewheel_repo_windows/configure_domain/vm_resources/add_activedirectory_users.ps1
firewheel_repo_windows-2.7.0.dist-info/LICENSE
firewheel_repo_windows-2.7.0.dist-info/METADATA
firewheel_repo_windows-2.7.0.dist-info/WHEEL
firewheel_repo_windows-2.7.0.dist-info/entry_points.txt
firewheel_repo_windows-2.7.0.dist-info/top_level.txt
firewheel_repo_windows-2.7.0.dist-info/RECORD
